ops/__init__.py
ops/_main.py
ops/charm.py
ops/framework.py
ops/jujucontext.py
ops/jujuversion.py
ops/log.py
ops/main.py
ops/model.py
ops/pebble.py
ops/py.typed
ops/storage.py
ops/testing.py
ops/version.py
ops/_private/__init__.py
ops/_private/harness.py
ops/_private/timeconv.py
ops/_private/yaml.py
ops/hookcmds/__init__.py
ops/hookcmds/_action.py
ops/hookcmds/_other.py
ops/hookcmds/_port.py
ops/hookcmds/_relation.py
ops/hookcmds/_secret.py
ops/hookcmds/_state.py
ops/hookcmds/_status.py
ops/hookcmds/_storage.py
ops/hookcmds/_types.py
ops/hookcmds/_utils.py
ops/lib/__init__.py
ops-3.5.0.dist-info/licenses/LICENSE.txt
ops-3.5.0.dist-info/METADATA
ops-3.5.0.dist-info/WHEEL
ops-3.5.0.dist-info/top_level.txt
ops-3.5.0.dist-info/RECORD
