Metadata-Version: 2.4
Name: ops
Version: 3.5.0
Summary: The Python library behind great charms
Author: The Charm Tech team at Canonical Ltd.
License-Expression: Apache-2.0
Project-URL: Homepage, https://documentation.ubuntu.com/ops/latest/
Project-URL: Repository, https://github.com/canonical/operator
Project-URL: Issues, https://github.com/canonical/operator/issues
Project-URL: Documentation, https://documentation.ubuntu.com/ops/latest/
Project-URL: Changelog, https://github.com/canonical/operator/blob/main/CHANGES.md
Classifier: Programming Language :: Python :: 3
Classifier: Development Status :: 5 - Production/Stable
Classifier: Intended Audience :: Developers
Classifier: Intended Audience :: System Administrators
Classifier: Operating System :: MacOS :: MacOS X
Classifier: Operating System :: POSIX :: Linux
Requires-Python: >=3.10
License-File: LICENSE.txt
Requires-Dist: PyYAML==6.*
Requires-Dist: websocket-client==1.*
Requires-Dist: opentelemetry-api~=1.0
Provides-Extra: testing
Requires-Dist: ops-scenario==8.5.0; extra == "testing"
Provides-Extra: tracing
Requires-Dist: ops-tracing==3.5.0; extra == "tracing"
Provides-Extra: harness
Dynamic: license-file
